README.md
setup.py
test/test_kline_analyst.py
test/test_plate.py
test/test_stock_pool.py
tma/__init__.py
tma/plate.py
tma/pool.py
tma/share.py
tma/utils.py
tma.egg-info/PKG-INFO
tma.egg-info/SOURCES.txt
tma.egg-info/dependency_links.txt
tma.egg-info/requires.txt
tma.egg-info/top_level.txt
tma/analyst/__init__.py
tma/analyst/kline.py
tma/analyst/market.py
tma/analyst/news.py
tma/analyst/rank.py
tma/collector/__init__.py
tma/collector/cninfo.py
tma/collector/ts.py
tma/collector/xhn.py
tma/collector/xueqiu.py