Metadata-Version: 1.2
Name: tma
Version: 0.3.3
Summary: Tools for Market A - A股工具集
Home-page: https://github.com/zengbin93/TMA
Author: zengbin
Author-email: zeng_bin8888@163.com
License: MIT License
Keywords: A股,TuShare,交易数据分析,A股数据分析
Platform: UNKNOWN
Requires-Python: >=3
